memory_analyzer/__init__.py
memory_analyzer/analysis_utils.py
memory_analyzer/gdb_commands.py
memory_analyzer/integrationtest.py
memory_analyzer/memory_analyzer.py
memory_analyzer/frontend/__init__.py
memory_analyzer/frontend/frontend_utils.py
memory_analyzer/frontend/memanz_curses.py
memory_analyzer/templates/analysis.py.template
memory_analyzer/tests/__init__.py
memory_analyzer/tests/__main__.py
memory_analyzer/tests/test_analysis_template.py
memory_analyzer/tests/test_analysis_utils.py
memory_analyzer/tests/test_curses.py
memory_analyzer/tests/test_frontend.py
memory_analyzer/tests/test_gdb_commands.py
memory_analyzer/tests/test_main_lib.py
memory_analyzer-0.1.2.dist-info/LICENSE
memory_analyzer-0.1.2.dist-info/METADATA
memory_analyzer-0.1.2.dist-info/WHEEL
memory_analyzer-0.1.2.dist-info/entry_points.txt
memory_analyzer-0.1.2.dist-info/top_level.txt
memory_analyzer-0.1.2.dist-info/RECORD
