Metadata-Version: 2.1
Name: memory-analyzer
Version: 0.1.2
Summary: Python 3 memory analyzer for running processes
Home-page: https://github.com/facebookincubator/memory-analyzer
Author: Lisa Roach, Facebook
Author-email: lisroach@fb.com
License: MIT
Platform: UNKNOWN
Classifier: Development Status :: 1 - Planning
Classifier: Intended Audience :: Developers
Classifier: License :: OSI Approved :: MIT License
Classifier: Programming Language :: Python
Classifier: Programming Language :: Python :: 3
Classifier: Programming Language :: Python :: 3.6
Classifier: Programming Language :: Python :: 3.7
Requires-Python: >=3.6
Requires-Dist: click
Requires-Dist: attrs
Requires-Dist: jinja2
Requires-Dist: prettytable
Requires-Dist: pympler
Requires-Dist: objgraph
